sahara_plugin_spark/__init__.py
sahara_plugin_spark/i18n.py
sahara_plugin_spark/locale/de/LC_MESSAGES/sahara_plugin_spark.po
sahara_plugin_spark/locale/en_GB/LC_MESSAGES/sahara_plugin_spark.po
sahara_plugin_spark/locale/id/LC_MESSAGES/sahara_plugin_spark.po
sahara_plugin_spark/locale/ne/LC_MESSAGES/sahara_plugin_spark.po
sahara_plugin_spark/plugins/__init__.py
sahara_plugin_spark/plugins/spark/__init__.py
sahara_plugin_spark/plugins/spark/config_helper.py
sahara_plugin_spark/plugins/spark/edp_engine.py
sahara_plugin_spark/plugins/spark/images.py
sahara_plugin_spark/plugins/spark/plugin.py
sahara_plugin_spark/plugins/spark/run_scripts.py
sahara_plugin_spark/plugins/spark/scaling.py
sahara_plugin_spark/plugins/spark/shell_engine.py
sahara_plugin_spark/plugins/spark/resources/README.rst
sahara_plugin_spark/plugins/spark/resources/core-default.xml
sahara_plugin_spark/plugins/spark/resources/hdfs-default.xml
sahara_plugin_spark/plugins/spark/resources/spark-cleanup.cron
sahara_plugin_spark/plugins/spark/resources/spark-env.sh.template
sahara_plugin_spark/plugins/spark/resources/tmp-cleanup.sh.template
sahara_plugin_spark/plugins/spark/resources/topology.sh
sahara_plugin_spark/plugins/spark/resources/images/image.yaml
sahara_plugin_spark/plugins/spark/resources/images/centos/turn_off_services
sahara_plugin_spark/plugins/spark/resources/images/centos/wget_cdh_repo
sahara_plugin_spark/plugins/spark/resources/images/common/add_jar
sahara_plugin_spark/plugins/spark/resources/images/common/install_extjs
sahara_plugin_spark/plugins/spark/resources/images/common/install_spark
sahara_plugin_spark/plugins/spark/resources/images/common/manipulate_s3
sahara_plugin_spark/plugins/spark/resources/images/ubuntu/config_spark
sahara_plugin_spark/plugins/spark/resources/images/ubuntu/turn_off_services
sahara_plugin_spark/plugins/spark/resources/images/ubuntu/wget_cdh_repo
sahara_plugin_spark/tests/__init__.py
sahara_plugin_spark/tests/unit/__init__.py
sahara_plugin_spark-10.0.0.dist-info/AUTHORS
sahara_plugin_spark-10.0.0.dist-info/LICENSE
sahara_plugin_spark-10.0.0.dist-info/METADATA
sahara_plugin_spark-10.0.0.dist-info/WHEEL
sahara_plugin_spark-10.0.0.dist-info/entry_points.txt
sahara_plugin_spark-10.0.0.dist-info/pbr.json
sahara_plugin_spark-10.0.0.dist-info/top_level.txt
sahara_plugin_spark-10.0.0.dist-info/RECORD
