Metadata-Version: 2.1
Name: sahara-plugin-spark
Version: 10.0.0
Summary: Spark Plugin for Sahara Project
Home-page: https://docs.openstack.org/sahara/latest/
Author: OpenStack
Author-email: openstack-discuss@lists.openstack.org
License: Apache Software License
Platform: UNKNOWN
Classifier: Programming Language :: Python
Classifier: Programming Language :: Python :: Implementation :: CPython
Classifier: Programming Language :: Python :: 3 :: Only
Classifier: Programming Language :: Python :: 3
Classifier: Programming Language :: Python :: 3.8
Classifier: Programming Language :: Python :: 3.9
Classifier: Environment :: OpenStack
Classifier: Intended Audience :: Information Technology
Classifier: Intended Audience :: System Administrators
Classifier: License :: OSI Approved :: Apache Software License
Classifier: Operating System :: POSIX :: Linux
Requires-Python: >=3.8
Requires-Dist: Babel (!=2.4.0,>=2.3.4)
Requires-Dist: eventlet (>=0.26.0)
Requires-Dist: oslo.i18n (>=3.15.3)
Requires-Dist: oslo.log (>=3.36.0)
Requires-Dist: oslo.serialization (!=2.19.1,>=2.18.0)
Requires-Dist: oslo.utils (>=3.33.0)
Requires-Dist: pbr (!=2.1.0,>=2.0.0)
Requires-Dist: requests (>=2.14.2)
Requires-Dist: sahara (>=10.0.0.0b1)
Requires-Dist: six (>=1.10.0)
